A365/__init__.py
Py_A365-0.0.0a1.dist-info/METADATA
Py_A365-0.0.0a1.dist-info/WHEEL
Py_A365-0.0.0a1.dist-info/top_level.txt
Py_A365-0.0.0a1.dist-info/RECORD
